tmux_schmooze/__init__.py
tmux_schmooze/__main__.py
tmux_schmooze/tmux.py
tmux_schmooze/ui.py
tmux_schmooze-0.1.2.dist-info/entry_points.txt
tmux_schmooze-0.1.2.dist-info/WHEEL
tmux_schmooze-0.1.2.dist-info/METADATA
tmux_schmooze-0.1.2.dist-info/RECORD
