Metadata-Version: 2.1
Name: tmux-schmooze
Version: 0.1.2
Summary: 
License: MIT
Author: Cam Graff
Author-email: graffcameron@gmail.com
Requires-Python: >=3.7,<4.0
Classifier: License :: OSI Approved :: MIT License
Classifier: Programming Language :: Python :: 3
Classifier: Programming Language :: Python :: 3.10
Classifier: Programming Language :: Python :: 3.7
Classifier: Programming Language :: Python :: 3.8
Classifier: Programming Language :: Python :: 3.9
Requires-Dist: click (>=8.0.3,<9.0.0)
Requires-Dist: fuzzyfinder (>=2.1.0,<3.0.0)
Requires-Dist: textual (>=0.1.12,<0.2.0)
